clicov/__init__.py
clicov/clicov.py
clicov/utils/__init__.py
clicov/utils/search.py
clicov-0.0.11.dist-info/LICENSE
clicov-0.0.11.dist-info/METADATA
clicov-0.0.11.dist-info/WHEEL
clicov-0.0.11.dist-info/entry_points.txt
clicov-0.0.11.dist-info/top_level.txt
clicov-0.0.11.dist-info/RECORD
