Metadata-Version: 2.1
Name: clicov
Version: 0.0.11
Summary: A command-line application to track COVID-19 cases
Home-page: https://github.com/hhandika/clicov
Author: Heru Handika
Author-email: hhandika.us@gmail.com
License: UNKNOWN
Platform: UNKNOWN
Classifier: Programming Language :: Python :: 3.6
Classifier: Programming Language :: Python :: 3.7
Classifier: License :: OSI Approved :: MIT License
Classifier: Operating System :: OS Independent
Classifier: Intended Audience :: End Users/Desktop
Classifier: Intended Audience :: Education
Classifier: Intended Audience :: Science/Research
Requires-Python: >=3.6
Requires-Dist: Click
Requires-Dist: pandas
Requires-Dist: requests
Requires-Dist: tabulate
